zope.securitypolicy-5.0-py3.9-nspkg.pth
zope/securitypolicy/__init__.py
zope/securitypolicy/configure.zcml
zope/securitypolicy/grantinfo.py
zope/securitypolicy/interfaces.py
zope/securitypolicy/meta.zcml
zope/securitypolicy/metaconfigure.py
zope/securitypolicy/metadirectives.py
zope/securitypolicy/principalpermission.py
zope/securitypolicy/principalrole.py
zope/securitypolicy/role.py
zope/securitypolicy/rolepermission.py
zope/securitypolicy/securitymap.py
zope/securitypolicy/securitypolicy.zcml
zope/securitypolicy/settings.py
zope/securitypolicy/vocabulary.py
zope/securitypolicy/zopepolicy.py
zope/securitypolicy/zopepolicy.txt
zope/securitypolicy/tests/__init__.py
zope/securitypolicy/tests/deny_mapping.zcml
zope/securitypolicy/tests/grantall_mapping.zcml
zope/securitypolicy/tests/mapping.zcml
zope/securitypolicy/tests/permission_and_permissions.zcml
zope/securitypolicy/tests/role.zcml
zope/securitypolicy/tests/role_duplicate.zcml
zope/securitypolicy/tests/test_annotationprincipalpermissionmanager.py
zope/securitypolicy/tests/test_annotationprincipalrolemanager.py
zope/securitypolicy/tests/test_annotationrolepermissionmanager.py
zope/securitypolicy/tests/test_grantinfo.py
zope/securitypolicy/tests/test_principalpermissionmanager.py
zope/securitypolicy/tests/test_principalrolemanager.py
zope/securitypolicy/tests/test_role.py
zope/securitypolicy/tests/test_rolepermissionmanager.py
zope/securitypolicy/tests/test_securitydirectives.py
zope/securitypolicy/tests/test_securitymap.py
zope/securitypolicy/tests/test_settings.py
zope/securitypolicy/tests/test_vocabulary.py
zope/securitypolicy/tests/test_zopepolicy.py
zope.securitypolicy-5.0.dist-info/LICENSE.txt
zope.securitypolicy-5.0.dist-info/METADATA
zope.securitypolicy-5.0.dist-info/WHEEL
zope.securitypolicy-5.0.dist-info/namespace_packages.txt
zope.securitypolicy-5.0.dist-info/top_level.txt
zope.securitypolicy-5.0.dist-info/RECORD
